english_improver/__init__.py
english_improver/constants.py
english_improver/example_usage.py
english_improver/gutenberg_scraper.py
english_improver/markov_chain_generator.py
english_improver/pdf_generator.py
english_improver-0.2.0.dist-info/METADATA
english_improver-0.2.0.dist-info/WHEEL
english_improver-0.2.0.dist-info/entry_points.txt
english_improver-0.2.0.dist-info/RECORD
