Metadata-Version: 2.4
Name: english-improver
Version: 0.2.0
Summary: An library to improve your english proficiency skills.
Author-email: Vishy Gopal <112359514+VG-Fish@users.noreply.github.com>
Requires-Python: >=3.13.0
